{"VcDozW3f+XWFYzXfBSAIDg==":"untitled-design-1.png","E1+ElwVjbSn/Fo3ouJRraw==":"mbr.jpg","l52dpcGk1GHDNbo8x8XdEg==":"mbr-1.jpg","j3Vr9EI2Egv3X0AofQHXBg==":"2.png","NF7VXsPSHbma0JJX1mzk4w==":"6.png","RBJPcV8m5LMOMA5eO0yNBA==":"3.png","gaD65k58ltpshrkBz9PRZQ==":"5.png","MDekgHyxyaKbhy+UZk60NQ==":"4.png","xUIsOtOTdym6hOWroT2lkw==":"untitled-design-2.png","h+pwRq/HmmwhDyhikoWO0w==":"untitled%20design%20(3)-1080x1080.png","2O1dpJsinhX0qQSyfbozug==":"untitled%20design%20(4)-1080x1080.png","et+CtENLS10+5bnhgvo7OQ==":"untitled%20design%20(5)-1080x1080.png","owTdvU/t2B8t1vGx+HtW1Q==":"untitled%20design%20(6)-1080x1080.png","Wn9KHkhkLhlGD1Lpu5gVFg==":"untitled%20design%20(7)-1080x1080.png","wYUsLusKJIYTa0A73HsvMQ==":"untitled%20design%20(8)-1080x1080.png","g3AkXvRk4s4lUkIIMwWnmg==":"untitled%20design%20(9)-1080x1080.png","79lyuahilgjNaPplsL8BYQ==":"untitled%20design%20(10)-1080x1080.png","NRXChMZwdoeL7T9zSisATQ==":"untitled%20design%20(11)-1080x1080.png","jRm51Dl7XDPgzu/Mb60Hbg==":"untitled%20design%20(12)-1080x1080.png","x7yFyNx1s+SXbHe4GDOYvg==":"untitled%20design%20(13)-1080x1080.png","L4bBaYyXUoSkBmhkK4bORA==":"untitled%20design%20(14)-1080x1080.png","/03l+FEZ3QRIIL+MR0oo4w==":"untitled%20design%20(15)-1080x1080.png","BhPci52E/MFeVj4Fp7RQlA==":"untitled%20design%20(15)-1080x1080.png","yTl2rp+IhNsQhRetziolKw==":"untitled%20design%20(16)-1080x1080.png","NRdzDF26NCwDKwnoBmwHtQ==":"untitled%20design%20(17)-1080x1080.png","M1l9qxk71xJOu/R/RW41oQ==":"untitled%20design%20(18)-1080x1080.png","K9Wi9JayDQnMB5VX4zroQw==":"untitled%20design%20(19)-1080x1080.png","8cKATkLuktudHjlFdUzlrQ==":"untitled%20design%20(20)-1080x1080.png","5Fxl2Heo69C6owTdhJ9+fQ==":"untitled%20design%20(21)-1080x1080.png","wlXrbL8RJXDAHdGE+ByMeg==":"untitled%20design%20(22)-816x816.png","xVBeI7+U0lD3GvDhxwGltw==":"untitled%20design%20(21)-816x816.png","vRjN/7/SdW1R7myLyUKTLQ==":"untitled%20design%20(23)-816x816.png","Xt1RJz1WLHgl0Ksbj729HQ==":"untitled%20design%20(24)-600x600.png","YpE1JZkNO+5bsAaAcrWRjg==":"untitled%20design%20(27)-600x600.png","dIVOHQ16ehh4akJAC9ZpiA==":"untitled%20design%20(25)-600x600.png","jT6bvoLusI6I0U0RWr17Dg==":"untitled%20design%20(26)-600x600.png","eXkkjriapKcxgJHtOdM2CQ==":"untitled%20design%20(24)-400x400.png","qBNSFcwkDBiKBl5Vil4fwQ==":"320225920_688882399458117_7439946849279015365_n-2048x1536.jpeg","EcMEuQMWlQk72B+lbAEUQQ==":"320225920_688882399458117_7439946849279015365_n-2000x1500.jpeg","6ZeaOfG1wxuJpMH3be7CtA==":"320225920_688882399458117_7439946849279015365_n-1-2000x1500.jpeg","al7Zh11fPhOIbYM5Dw2Gtg==":"untitled%20design%20(30)-1080x1080.png","skoXdSkkOnFDJeZpldHzgg==":"untitled%20design%20(31)-2000x1000.png","u7J3I2+lYy/sDxWs76NrBw==":"untitled%20design%20(32)-2000x1000.png","nMRN2tds46YHKZ9KhYMZ2g==":"untitled%20design%20(33)-2000x1000.png","7bQ0CGOAZgXpf21NHWoOTg==":"untitled%20design%20(34)-2000x1000.png","xCdLmC6qpProju3O9em2ZA==":"untitled%20design%20(29)-1080x1080.png","WZM5O3f9LI/Cuj3x5+zA9Q==":"untitled%20design%20(35)-1080x1080.png","MwmOHRcpw+6GENCS2k6dCA==":"untitled%20design%20(36)-1080x1080.png","iC3IE6X/zVtBUQJcoX+A8w==":"untitled%20design%20(37)-1080x1080.png","J2TG2pxydCpQR79iU6JXPQ==":"untitled%20design%20(38)-1080x1080.png","q8OjVHoYDltZGQ4kOQdBGg==":"untitled%20design%20(39)-1080x1080.png","dgT2ornQGdAsRFAHMzOdpg==":"welcome-858x858.png","Q2WmkeKbXq7GwAiZSAdf8g==":"welcome%20(2)-858x858.png","wSn3D9ZWDxQwFGBmPVUXFg==":"welcome%20(3)-858x858.png","PEfWO7+HNl5fhgY2nvv1PA==":"martha-maria%20(7)-169x169.png","PKyX/gD+CgKbKUzhk3Pgrg==":"untitled%20design%20(1)-2000x1000.png","DpIBx2QOuHZ19IT1MJu4VQ==":"img-3638-1256x1675.jpeg","oRykAiO0rUD++7AmPeEwUg==":"background1.jpg","n1dx+NZv3qks526xC0hZ5Q==":"background13.jpg","ZoKRsguLhykidQ3eFHOdlw==":"welcome%20(4)-858x858.png","8LP6EzU7NMASx94MGRTRmQ==":"martha-maria%20(8)-256x256.png"}